Verilog/ddsmini.v
module smart_irrigation #(
    parameter NUM_USERS = 4,
    parameter WIDTH = 6, // 6-bit (0-63)
    parameter DEBOUNCE_WIDTH = 20
)(
    // --- System Inputs ---
    input  wire clk,                // Main fast clock
    input  wire rst_n,              // Active low reset
    input  wire clk_1hz,            // 1-second clock for 24-hour timer

    // --- Sensor Inputs ---
    input  wire flow_pulse_raw,    // Flow sensor pulse
    input  wire moisture_dry,      // 1 = dry
    input  wire rain,              // 1 = raining

    // --- Control Inputs ---
    input  wire auto_cycle_start,           // Start automatic sequence
    input  wire [1:0] user_select_manual,   // Manual zone select
    input  wire reset_user,                 // reset usage for CURRENT user
    input  wire quota_wr,                   // write quota for CURRENT user
    input  wire [WIDTH-1:0] quota_set,      // quota value to write
    input  wire manual_override,            // force valve on (except rain/exhausted)

    // --- System Outputs ---
    output reg  valve_on,
    output reg  [NUM_USERS-1:0] quota_exceeded,
    output reg  [WIDTH-1:0]     usage_out,
    output reg  [WIDTH-1:0]     quota_out,
    output wire flow_boost_on,
    output wire sequencer_active,
    output wire [1:0] current_zone
);

    //================================================================
    // 1. MEMORY AND DATA REGISTERS
    //================================================================
    reg [WIDTH-1:0] quota [0:NUM_USERS-1];
    reg [WIDTH-1:0] usage [0:NUM_USERS-1];
    integer i;

    //================================================================
    // 2. 24-HOUR CLOCK & PEAK TIME LOGIC
    //================================================================
    reg [4:0] hour_cnt; // 0-23 fits in 5 bits
    wire peak_time;

    // hour counter increments on posedge clk_1hz (clean pulse)
    always @(posedge clk_1hz or negedge rst_n) begin
        if (!rst_n) begin
            hour_cnt <= 0;
        end else begin
            if (hour_cnt == 23)
                hour_cnt <= 0;
            else
                hour_cnt <= hour_cnt + 1;
        end
    end

    assign peak_time = (hour_cnt >= 5'd10) && (hour_cnt <= 5'd16);

    //================================================================
    // 3. PRIORITY ZONE SEQUENCER (FSM)
    //================================================================
    localparam [2:0] S_IDLE   = 3'b000;
    localparam [2:0] S_ZONE_2 = 3'b001; // Priority 1: zone 2 (10)
    localparam [2:0] S_ZONE_0 = 3'b010; // Priority 2: zone 0 (00)
    localparam [2:0] S_ZONE_3 = 3'b011; // Priority 3: zone 3 (11)
    localparam [2:0] S_ZONE_1 = 3'b100; // Priority 4: zone 1 (01)

    reg [2:0] current_state;

    reg [1:0] internal_user_select_fsm;
    reg       internal_start_pulse;
    reg       internal_sequencer_active;

    // For edge detection of irrigating -> not-irrigating
    reg irrigating_last;

    // zone_finished pulse is true when irrigating was 1 last cycle and now 0
    wire zone_finished_pulse = irrigating_last && !irrigating;

    // Sequencer FSM (clocked by main clk)
    always @(posedge clk or negedge rst_n) begin
        if (!rst_n) begin
            current_state <= S_IDLE;
            internal_start_pulse <= 1'b0;
        end else begin
            internal_start_pulse <= 1'b0; // default: 1-cycle pulse when asserted
            case (current_state)
                S_IDLE: begin
                    if (auto_cycle_start) begin
                        current_state <= S_ZONE_2;
                        internal_start_pulse <= 1'b1;
                    end
                end
                S_ZONE_2: begin
                    if (zone_finished_pulse) begin
                        current_state <= S_ZONE_0;
                        internal_start_pulse <= 1'b1;
                    end
                end
                S_ZONE_0: begin
                    if (zone_finished_pulse) begin
                        current_state <= S_ZONE_3;
                        internal_start_pulse <= 1'b1;
                    end
                end
                S_ZONE_3: begin
                    if (zone_finished_pulse) begin
                        current_state <= S_ZONE_1;
                        internal_start_pulse <= 1'b1;
                    end
                end
                S_ZONE_1: begin
                    if (zone_finished_pulse) begin
                        current_state <= S_IDLE;
                    end
                end
                default: current_state <= S_IDLE;
            endcase
        end
    end

    // Combinational outputs for FSM state
    always @(*) begin
        case (current_state)
            S_IDLE:   begin internal_user_select_fsm = 2'b00; internal_sequencer_active = 1'b0; end
            S_ZONE_2: begin internal_user_select_fsm = 2'b10; internal_sequencer_active = 1'b1; end
            S_ZONE_0: begin internal_user_select_fsm = 2'b00; internal_sequencer_active = 1'b1; end
            S_ZONE_3: begin internal_user_select_fsm = 2'b11; internal_sequencer_active = 1'b1; end
            S_ZONE_1: begin internal_user_select_fsm = 2'b01; internal_sequencer_active = 1'b1; end
            default:  begin internal_user_select_fsm = 2'b00; internal_sequencer_active = 1'b0; end
        endcase
    end

    // Final user select: FSM (if active) or manual select
    wire [1:0] final_user_select = internal_sequencer_active ? internal_user_select_fsm : user_select_manual;

    assign sequencer_active = internal_sequencer_active;
    assign current_zone = final_user_select;

    //================================================================
    // 4. DEBOUNCE PULSE
    //================================================================
    wire flow_pulse_debounced;
    debounce_pulse #(.WIDTH(DEBOUNCE_WIDTH)) u_debounce (
        .clk(clk),
        .rst_n(rst_n),
        .raw_in(flow_pulse_raw),
        .clean_out(flow_pulse_debounced)
    );

    //================================================================
    // 5. CORE CONTROLLER LOGIC
    //================================================================
    reg irrigating;
    reg flow_pulse_last;

    // increment value: 2 during peak_time else 1
    wire [1:0] increment_val = peak_time ? 2'b10 : 2'b01;

    // max value of WIDTH bits
    wire [WIDTH-1:0] max_val = {WIDTH{1'b1}};

    // Reset and main sequential behavior
    always @(posedge clk or negedge rst_n) begin
        if (!rst_n) begin
            irrigating <= 1'b0;
            flow_pulse_last <= 1'b0;
            irrigating_last <= 1'b0;
            // Clear memories on reset
            for (i = 0; i < NUM_USERS; i = i + 1) begin
                usage[i] <= {WIDTH{1'b0}};
                quota[i] <= {WIDTH{1'b0}};
            end
            // outputs
            usage_out <= {WIDTH{1'b0}};
            quota_out <= {WIDTH{1'b0}};
        end else begin
            // track previous pulse and irrigating state
            flow_pulse_last <= flow_pulse_debounced;
            irrigating_last <= irrigating;

            // handle writes/resets targeted at final_user_select
            if (reset_user) begin
                usage[final_user_select] <= {WIDTH{1'b0}};
            end

            if (quota_wr) begin
                quota[final_user_select] <= quota_set;
            end

            // Starting condition: a 1-cycle internal_start_pulse triggers irrigating start,
            // but we also check moisture_dry, rain, and quota_exceeded
            if (internal_start_pulse && !irrigating && moisture_dry && !rain && !quota_exceeded[final_user_select]) begin
                irrigating <= 1'b1;
            end
            // Stop conditions
            else if (irrigating && (!moisture_dry || rain || quota_exceeded[final_user_select])) begin
                irrigating <= 1'b0;
            end

            // Count rising edge of debounced flow pulse if valve_on is true
            if (valve_on && flow_pulse_debounced && !flow_pulse_last) begin
                // safe add with overflow clamp
                if (usage[final_user_select] <= max_val - {{(WIDTH-2){1'b0}}, increment_val}) begin
                    usage[final_user_select] <= usage[final_user_select] + {{(WIDTH-2){1'b0}}, increment_val};
                end else begin
                    usage[final_user_select] <= max_val;
                end
            end

            // Update outputs for currently selected user (registered output)
            usage_out <= usage[final_user_select];
            quota_out <= quota[final_user_select];
        end
    end

    // Quota exceeded combinational
    always @(*) begin
        for (i = 0; i < NUM_USERS; i = i + 1) begin
            quota_exceeded[i] = (usage[i] >= quota[i]);
        end
    end

    // Valve control combinational
    always @(*) begin
        if (rain) begin
            valve_on = 1'b0; // rain overrides everything
        end else if (manual_override && !quota_exceeded[final_user_select]) begin
            valve_on = 1'b1;
        end else if (irrigating && !quota_exceeded[final_user_select]) begin
            valve_on = 1'b1;
        end else begin
            valve_on = 1'b0;
        end
    end

    assign flow_boost_on = valve_on && peak_time;

endmodule


// Debounce module (unchanged; kept as reg output)
module debounce_pulse #(
    parameter WIDTH = 20
)(
    input wire clk,
    input wire rst_n,
    input wire raw_in,
    output reg clean_out
);
    reg [WIDTH-1:0] counter;
    reg raw_sync_0;
    reg raw_sync_1;

    always @(posedge clk or negedge rst_n) begin
        if (!rst_n) begin
            raw_sync_0 <= 1'b0;
            raw_sync_1 <= 1'b0;
            counter    <= {WIDTH{1'b0}};
            clean_out  <= 1'b0;
        end else begin
            raw_sync_0 <= raw_in;
            raw_sync_1 <= raw_sync_0;

            if (raw_sync_1 == clean_out) begin
                counter <= {WIDTH{1'b0}};
            end else begin
                if (counter != {WIDTH{1'b1}}) begin
                    counter <= counter + 1'b1;
                end else begin
                    clean_out <= raw_sync_1;
                    counter <= {WIDTH{1'b0}};
                end
            end
        end
    end
endmodule

Verilog/ddsmini_tb.v
`timescale 1ns/1ps
module tb_smart_irrigation_auto;

    // --- System Clocks & Reset ---
    reg clk = 0;
    reg rst_n = 0;
    reg clk_1hz = 0; // 1-second clock pulse

    // --- Sensor Inputs ---
    reg flow_pulse_raw = 0;
    reg moisture_dry = 0;
    reg rain = 0;

    // --- Control Inputs ---
    reg auto_cycle_start = 0;
    reg [1:0] user_select_manual = 0; // NEW: For admin tasks
    reg reset_user = 0;
    reg quota_wr = 0;
    reg [5:0] quota_set = 0; // WIDTH is 6
    reg manual_override = 0;

    // --- System Outputs ---
    wire valve_on;
    wire [3:0] quota_exceeded;
    wire [5:0] usage_out; // WIDTH is 6
    wire [5:0] quota_out; // WIDTH is 6
    wire flow_boost_on;
    wire sequencer_active;
    wire [1:0] current_zone;

    // Instantiate DUT (Design Under Test)
    smart_irrigation #(
        .NUM_USERS(4),
        .WIDTH(6),          // <-- UPDATED
        .DEBOUNCE_WIDTH(3)  // Override to 3 (requires 2^3=8 clock stable time)
    ) DUT (
        .clk(clk),
        .rst_n(rst_n),
        .clk_1hz(clk_1hz), // <-- NEW
        .flow_pulse_raw(flow_pulse_raw),
        .moisture_dry(moisture_dry),
        .rain(rain),
        .auto_cycle_start(auto_cycle_start), // <-- NEW
        .user_select_manual(user_select_manual), // <-- NEW
        .reset_user(reset_user),
        .quota_wr(quota_wr),
        .quota_set(quota_set),
        .manual_override(manual_override),
        .valve_on(valve_on),
        .quota_exceeded(quota_exceeded),
        .usage_out(usage_out),
        .quota_out(quota_out),
        .flow_boost_on(flow_boost_on),     // <-- NEW
        .sequencer_active(sequencer_active), // <-- NEW
        .current_zone(current_zone)          // <-- NEW
    );

    // --- Clock Generation ---
    // 10ns period clock (100MHz)
    always #5 clk = ~clk;

    // --- Helper Tasks ---
    task pulse_flow;
        begin
            @(posedge clk);
            flow_pulse_raw = 1;
            repeat(10) @(posedge clk); // Hold for 10 cycles (longer than 2^3=8)
            flow_pulse_raw = 0;
            repeat(10) @(posedge clk); // Wait for pulse to clear debouncer
        end
    endtask

    // Helper task to pulse the 1-second clock
    task pulse_1hz;
        begin
            @(posedge clk); // Sync to main clock
            clk_1hz = 1;
            @(posedge clk);
            clk_1hz = 0;
        end
    endtask

    // Helper task to set quota for a specific zone
    task set_quota;
        input [1:0] zone;
        input [5:0] amount;
        begin
            user_select_manual = zone; // Select zone
            quota_set = amount;      // Set quota amount
            quota_wr = 1;            // Pulse write
            @(posedge clk);
            quota_wr = 0;
            @(posedge clk);
            $display("T=%0t: [Admin] Quota for Zone %0d set to %0d", $time, zone, quota_out);
        end
    endtask

    // --- Test Sequence ---
    initial begin
        // --- VCD Waveform Dump ---
        $dumpfile("smart_irrigation_auto.vcd");
        $dumpvars(0, tb_smart_irrigation_auto);

        $display("-----------------------------------------------------------------");
        $display("T=%0t: === Automated Irrigation Testbench ===", $time);
        $display("-----------------------------------------------------------------");
        
        // --- Monitor Task ---
        $monitor("T=%0t | Zone=%0d | S_Act=%b | V_On=%b | F_Boost=%b | Q_Ex=%4b | Usage=%0d | Quota=%0d | Rain=%b",
                 $time, current_zone, sequencer_active, valve_on, flow_boost_on, quota_exceeded, usage_out, quota_out, rain);

        // --- Part 1: Reset and Set Quotas ---
        rst_n = 0;
        #20;
        rst_n = 1;
        @(posedge clk);
        $display("\nT=%0t: System out of reset. Sequencer is IDLE.", $time);
        
        // While sequencer is IDLE, we can use user_select_manual to set quotas
        // Priority Order: Zone 2 -> 0 -> 3 -> 1
        set_quota(2, 10); // Prio 1: Zone 2 gets 10 pulses
        set_quota(0, 5);  // Prio 2: Zone 0 gets 5 pulses
        set_quota(3, 8);  // Prio 3: Zone 3 gets 8 pulses
        set_quota(1, 6);  // Prio 4: Zone 1 gets 6 pulses

        // --- Part 2: Test Automatic Sequence (No Peak Time) ---
        $display("\nT=%0t: === Test 2: Automatic Sequence (No Peak Time) ===", $time);
        moisture_dry = 1; // It's dry
        
        // Start the cycle
        auto_cycle_start = 1;
        @(posedge clk);
        auto_cycle_start = 0;
        @(posedge clk);
        
        $display("T=%0t: Auto cycle started. Waiting for Prio 1 (Zone 2)...", $time);
        
        // --- Prio 1: Zone 2 (Quota 10) ---
        repeat(10) pulse_flow();
        @(posedge clk); // Let FSM update
        $display("T=%0t: Zone 2 finished. Waiting for Prio 2 (Zone 0)...", $time);
        
        // --- Prio 2: Zone 0 (Quota 5) ---
        repeat(5) pulse_flow();
        @(posedge clk);
        $display("T=%0t: Zone 0 finished. Waiting for Prio 3 (Zone 3)...", $time);

        // --- Prio 3: Zone 3 (Quota 8) ---
        repeat(8) pulse_flow();
        @(posedge clk);
        $display("T=%0t: Zone 3 finished. Waiting for Prio 4 (Zone 1)...", $time);

        // --- Prio 4: Zone 1 (Quota 6) ---
        repeat(6) pulse_flow();
        @(posedge clk);
        $display("T=%0t: Zone 1 finished. Auto sequence complete.", $time);
        
        #50;
        if (sequencer_active) $error("Sequencer is still active after cycle!");
        if (valve_on) $error("Valve is still on after cycle!");

        // --- Part 3: Test Peak Time & Flow Boost (+2) ---
        $display("\nT=%0t: === Test 3: Peak Time & Flow Boost (+2) ===", $time);
        
        // Reset usage for all zones manually
        user_select_manual = 0; reset_user = 1; @(posedge clk); reset_user = 0;
        user_select_manual = 1; reset_user = 1; @(posedge clk); reset_user = 0;
        user_select_manual = 2; reset_user = 1; @(posedge clk); reset_user = 0;
        user_select_manual = 3; reset_user = 1; @(posedge clk); reset_user = 0;
        $display("T=%0t: All zone usage reset.", $time);

        // Advance 24hr clock to 10:00 (peak time)
        $display("T=%0t: Advancing clock to 10:00...", $time);
        repeat(10) pulse_1hz();
        
        // Start the cycle again, now in peak time
        auto_cycle_start = 1; @(posedge clk); auto_cycle_start = 0; @(posedge clk);
        $display("T=%0t: Auto cycle started. Prio 1 (Zone 2) should have +2 boost.", $time);
        
        // Prio 1: Zone 2 (Quota 10)
        // It should only take 5 pulses to meet quota (5 * 2 = 10)
        repeat(5) pulse_flow();
        @(posedge clk);
        
        if (usage_out != 10) $error("Flow boost failed! Usage is %0d, expected 10", usage_out);
        if (valve_on) $error("Valve did not shut off after 5 boosted pulses!");
        $display("T=%0t: Zone 2 finished with 5 boosted pulses. Correct.", $time);
        
        // Let the rest of the cycle finish (we don't care about it)
        #2000;
        rst_n = 0; #50; rst_n = 1; // Reset to stop cycle
        
        // --- Part 4: Test Rain & Manual Override ---
        $display("\nT=%0t: === Test 4: Rain & Manual Override ===", $time);
        moisture_dry = 1;
        user_select_manual = 0; // Select Zone 0
        manual_override = 1;
        @(posedge clk);
        $display("T=%0t: Manual Override ON. valve_on=%b (Should be 1)", $time, valve_on);
        
        rain = 1;
        @(posedge clk);
        $display("T=%0t: Rain ON. valve_on=%b (Should be 0)", $time, valve_on);
        
        rain = 0;
        @(posedge clk);
        $display("T=%0t: Rain OFF. valve_on=%b (Should be 1)", $time, valve_on);
        
        manual_override = 0;
        @(posedge clk);
        $display("T=%0t: Manual Override OFF. valve_on=%b (Should be 0)", $time, valve_on);

        $display("\n-----------------------------------------------------------------");
        $display("T=%0t: === Test Complete ===", $time);
        $display("-----------------------------------------------------------------");
        #50;
        $finish;
    end

endmodule

Verilog/smart_irrigation_auto.vcd
$date
	Sun Nov 02 20:28:02 2025
$end
$version
	Icarus Verilog
$end
$timescale
	1ps
$end
$scope module tb_smart_irrigation_auto $end
$var wire 1 ! valve_on $end
$var wire 6 " usage_out [5:0] $end
$var wire 1 # sequencer_active $end
$var wire 6 $ quota_out [5:0] $end
$var wire 4 % quota_exceeded [3:0] $end
$var wire 1 & flow_boost_on $end
$var wire 2 ' current_zone [1:0] $end
$var reg 1 ( auto_cycle_start $end
$var reg 1 ) clk $end
$var reg 1 * clk_1hz $end
$var reg 1 + flow_pulse_raw $end
$var reg 1 , manual_override $end
$var reg 1 - moisture_dry $end
$var reg 6 . quota_set [5:0] $end
$var reg 1 / quota_wr $end
$var reg 1 0 rain $end
$var reg 1 1 reset_user $end
$var reg 1 2 rst_n $end
$var reg 2 3 user_select_manual [1:0] $end
$scope module DUT $end
$var wire 1 ( auto_cycle_start $end
$var wire 1 ) clk $end
$var wire 1 * clk_1hz $end
$var wire 2 4 current_zone [1:0] $end
$var wire 1 & flow_boost_on $end
$var wire 1 + flow_pulse_raw $end
$var wire 1 , manual_override $end
$var wire 6 5 max_val [5:0] $end
$var wire 1 - moisture_dry $end
$var wire 1 6 peak_time $end
$var wire 6 7 quota_set [5:0] $end
$var wire 1 / quota_wr $end
$var wire 1 0 rain $end
$var wire 1 1 reset_user $end
$var wire 1 2 rst_n $end
$var wire 1 # sequencer_active $end
$var wire 2 8 user_select_manual [1:0] $end
$var wire 1 9 zone_finished_pulse $end
$var wire 2 : increment_val [1:0] $end
$var wire 1 ; flow_pulse_debounced $end
$var wire 2 < final_user_select [1:0] $end
$var parameter 32 = DEBOUNCE_WIDTH $end
$var parameter 32 > NUM_USERS $end
$var parameter 3 ? S_IDLE $end
$var parameter 3 @ S_ZONE_0 $end
$var parameter 3 A S_ZONE_1 $end
$var parameter 3 B S_ZONE_2 $end
$var parameter 3 C S_ZONE_3 $end
$var parameter 32 D WIDTH $end
$var reg 3 E current_state [2:0] $end
$var reg 1 F flow_pulse_last $end
$var reg 5 G hour_cnt [4:0] $end
$var reg 1 H internal_sequencer_active $end
$var reg 1 I internal_start_pulse $end
$var reg 2 J internal_user_select_fsm [1:0] $end
$var reg 1 K irrigating $end
$var reg 1 L irrigating_last $end
$var reg 4 M quota_exceeded [3:0] $end
$var reg 6 N quota_out [5:0] $end
$var reg 6 O usage_out [5:0] $end
$var reg 1 ! valve_on $end
$var integer 32 P i [31:0] $end
$scope module u_debounce $end
$var wire 1 ) clk $end
$var wire 1 + raw_in $end
$var wire 1 2 rst_n $end
$var parameter 32 Q WIDTH $end
$var reg 1 ; clean_out $end
$var reg 3 R counter [2:0] $end
$var reg 1 S raw_sync_0 $end
$var reg 1 T raw_sync_1 $end
$upscope $end
$upscope $end
$scope task pulse_1hz $end
$upscope $end
$scope task pulse_flow $end
$upscope $end
$scope task set_quota $end
$var reg 6 U amount [5:0] $end
$var reg 2 V zone [1:0] $end
$upscope $end
$upscope $end
$enddefinitions $end
$comment Show the parameter values. $end
$dumpall
b11 Q
b110 D
b11 C
b1 B
b100 A
b10 @
b0 ?
b100 >
b11 =
$end
#0
$dumpvars
bx V
bx U
0T
0S
b0 R
b100 P
b0 O
b0 N
b1111 M
0L
0K
b0 J
0I
0H
b0 G
0F
b0 E
b0 <
0;
b1 :
09
b0 8
b0 7
06
b111111 5
b0 4
b0 3
02
01
00
0/
b0 .
0-
0,
0+
0*
0)
0(
b0 '
0&
b1111 %
b0 $
0#
b0 "
0!
$end
#5000
b100 P
1)
#10000
0)
#15000
b100 P
1)
#20000
0)
12
#25000
b1110 %
b1110 M
b100 P
b10 '
b10 4
b10 <
1/
b1010 .
b1010 7
b10 3
b10 8
b1010 U
b10 V
1)
#30000
0)
#35000
0/
1)
#40000
0)
#45000
b1010 %
b1010 M
b100 P
b0 '
b0 4
b0 <
1/
b101 .
b101 7
b0 3
b0 8
b101 U
b0 V
1)
#50000
0)
#55000
b1010 $
b1010 N
0/
1)
#60000
0)
#65000
b100 P
b11 '
b11 4
b11 <
1/
b1000 .
b1000 7
b11 3
b11 8
b1000 U
b11 V
1)
#70000
0)
#75000
b0 $
b0 N
0/
1)
#80000
0)
#85000
b10 %
b10 M
b100 P
b1 '
b1 4
b1 <
1/
b110 .
b110 7
b1 3
b1 8
b110 U
b1 V
1)
#90000
0)
#95000
0/
1)
#100000
0)
#105000
b10 '
b10 4
b10 <
1#
1H
b10 J
1I
b1 E
1(
1-
1)
#110000
0)
#115000
1!
0I
b101 $
b101 N
1K
0(
1)
#120000
0)
#125000
1L
1)
#130000
0)
#135000
1S
1+
1)
#140000
0)
#145000
1T
1)
#150000
0)
#155000
b1 R
1)
#160000
0)
#165000
b10 R
1)
#170000
0)
#175000
b11 R
1)
#180000
0)
#185000
b100 R
1)
#190000
0)
#195000
b101 R
1)
#200000
0)
#205000
b110 R
1)
#210000
0)
#215000
b111 R
1)
#220000
0)
#225000
b0 R
1;
1)
#230000
0)
#235000
b100 P
0S
1F
0+
1)
#240000
0)
#245000
b1 "
b1 O
0T
1)
#250000
0)
#255000
b1 R
1)
#260000
0)
#265000
b10 R
1)
#270000
0)
#275000
b11 R
1)
#280000
0)
#285000
b100 R
1)
#290000
0)
#295000
b101 R
1)
#300000
0)
#305000
b110 R
1)
#310000
0)
#315000
b111 R
1)
#320000
0)
#325000
b0 R
0;
1)
#330000
0)
#335000
0F
1)
#340000
0)
#345000
1S
1+
1)
#350000
0)
#355000
1T
1)
#360000
0)
#365000
b1 R
1)
#370000
0)
#375000
b10 R
1)
#380000
0)
#385000
b11 R
1)
#390000
0)
#395000
b100 R
1)
#400000
0)
#405000
b101 R
1)
#410000
0)
#415000
b110 R
1)
#420000
0)
#425000
b111 R
1)
#430000
0)
#435000
b0 R
1;
1)
#440000
0)
#445000
b100 P
1F
0S
0+
1)
#450000
0)
#455000
0T
b10 "
b10 O
1)
#460000
0)
#465000
b1 R
1)
#470000
0)
#475000
b10 R
1)
#480000
0)
#485000
b11 R
1)
#490000
0)
#495000
b100 R
1)
#500000
0)
#505000
b101 R
1)
#510000
0)
#515000
b110 R
1)
#520000
0)
#525000
b111 R
1)
#530000
0)
#535000
b0 R
0;
1)
#540000
0)
#545000
0F
1)
#550000
0)
#555000
1S
1+
1)
#560000
0)
#565000
1T
1)
#570000
0)
#575000
b1 R
1)
#580000
0)
#585000
b10 R
1)
#590000
0)
#595000
b11 R
1)
#600000
0)
#605000
b100 R
1)
#610000
0)
#615000
b101 R
1)
#620000
0)
#625000
b110 R
1)
#630000
0)
#635000
b111 R
1)
#640000
0)
#645000
b0 R
1;
1)
#650000
0)
#655000
b100 P
0S
1F
0+
1)
#660000
0)
#665000
b11 "
b11 O
0T
1)
#670000
0)
#675000
b1 R
1)
#680000
0)
#685000
b10 R
1)
#690000
0)
#695000
b11 R
1)
#700000
0)
#705000
b100 R
1)
#710000
0)
#715000
b101 R
1)
#720000
0)
#725000
b110 R
1)
#730000
0)
#735000
b111 R
1)
#740000
0)
#745000
b0 R
0;
1)
#750000
0)
#755000
0F
1)
#760000
0)
#765000
1S
1+
1)
#770000
0)
#775000
1T
1)
#780000
0)
#785000
b1 R
1)
#790000
0)
#795000
b10 R
1)
#800000
0)
#805000
b11 R
1)
#810000
0)
#815000
b100 R
1)
#820000
0)
#825000
b101 R
1)
#830000
0)
#835000
b110 R
1)
#840000
0)
#845000
b111 R
1)
#850000
0)
#855000
b0 R
1;
1)
#860000
0)
#865000
b100 P
1F
0S
0+
1)
#870000
0)
#875000
0T
b100 "
b100 O
1)
#880000
0)
#885000
b1 R
1)
#890000
0)
#895000
b10 R
1)
#900000
0)
#905000
b11 R
1)
#910000
0)
#915000
b100 R
1)
#920000
0)
#925000
b101 R
1)
#930000
0)
#935000
b110 R
1)
#940000
0)
#945000
b111 R
1)
#950000
0)
#955000
b0 R
0;
1)
#960000
0)
#965000
0F
1)
#970000
0)
#975000
1S
1+
1)
#980000
0)
#985000
1T
1)
#990000
0)
#995000
b1 R
1)
#1000000
0)
#1005000
b10 R
1)
#1010000
0)
#1015000
b11 R
1)
#1020000
0)
#1025000
b100 R
1)
#1030000
0)
#1035000
b101 R
1)
#1040000
0)
#1045000
b110 R
1)
#1050000
0)
#1055000
b111 R
1)
#1060000
0)
#1065000
b0 R
1;
1)
#1070000
0)
#1075000
0!
b110 %
b110 M
b100 P
0S
1F
0+
1)
#1080000
0)
#1085000
19
b101 "
b101 O
0K
0T
1)
#1090000
0)
#1095000
b0 '
b0 4
b0 <
b0 J
09
b1 R
1I
b10 E
0L
1)
#1100000
0)
#1105000
1!
b1000 $
b1000 N
b0 "
b0 O
1K
0I
b10 R
1)
#1110000
0)
#1115000
b11 R
1L
1)
#1120000
0)
#1125000
b100 R
1)
#1130000
0)
#1135000
b101 R
1)
#1140000
0)
#1145000
b110 R
1)
#1150000
0)
#1155000
b111 R
1)
#1160000
0)
#1165000
b0 R
0;
1)
#1170000
0)
#1175000
0F
1)
#1180000
0)
#1185000
1S
1+
1)
#1190000
0)
#1195000
1T
1)
#1200000
0)
#1205000
b1 R
1)
#1210000
0)
#1215000
b10 R
1)
#1220000
0)
#1225000
b11 R
1)
#1230000
0)
#1235000
b100 R
1)
#1240000
0)
#1245000
b101 R
1)
#1250000
0)
#1255000
b110 R
1)
#1260000
0)
#1265000
b111 R
1)
#1270000
0)
#1275000
b0 R
1;
1)
#1280000
0)
#1285000
b100 P
1F
0S
0+
1)
#1290000
0)
#1295000
0T
b1 "
b1 O
1)
#1300000
0)
#1305000
b1 R
1)
#1310000
0)
#1315000
b10 R
1)
#1320000
0)
#1325000
b11 R
1)
#1330000
0)
#1335000
b100 R
1)
#1340000
0)
#1345000
b101 R
1)
#1350000
0)
#1355000
b110 R
1)
#1360000
0)
#1365000
b111 R
1)
#1370000
0)
#1375000
b0 R
0;
1)
#1380000
0)
#1385000
0F
1)
#1390000
0)
#1395000
1S
1+
1)
#1400000
0)
#1405000
1T
1)
#1410000
0)
#1415000
b1 R
1)
#1420000
0)
#1425000
b10 R
1)
#1430000
0)
#1435000
b11 R
1)
#1440000
0)
#1445000
b100 R
1)
#1450000
0)
#1455000
b101 R
1)
#1460000
0)
#1465000
b110 R
1)
#1470000
0)
#1475000
b111 R
1)
#1480000
0)
#1485000
b0 R
1;
1)
#1490000
0)
#1495000
b100 P
0S
1F
0+
1)
#1500000
0)
#1505000
b10 "
b10 O
0T
1)
#1510000
0)
#1515000
b1 R
1)
#1520000
0)
#1525000
b10 R
1)
#1530000
0)
#1535000
b11 R
1)
#1540000
0)
#1545000
b100 R
1)
#1550000
0)
#1555000
b101 R
1)
#1560000
0)
#1565000
b110 R
1)
#1570000
0)
#1575000
b111 R
1)
#1580000
0)
#1585000
b0 R
0;
1)
#1590000
0)
#1595000
0F
1)
#1600000
0)
#1605000
1S
1+
1)
#1610000
0)
#1615000
1T
1)
#1620000
0)
#1625000
b1 R
1)
#1630000
0)
#1635000
b10 R
1)
#1640000
0)
#1645000
b11 R
1)
#1650000
0)
#1655000
b100 R
1)
#1660000
0)
#1665000
b101 R
1)
#1670000
0)
#1675000
b110 R
1)
#1680000
0)
#1685000
b111 R
1)
#1690000
0)
#1695000
b0 R
1;
1)
#1700000
0)
#1705000
b100 P
1F
0S
0+
1)
#1710000
0)
#1715000
0T
b11 "
b11 O
1)
#1720000
0)
#1725000
b1 R
1)
#1730000
0)
#1735000
b10 R
1)
#1740000
0)
#1745000
b11 R
1)
#1750000
0)
#1755000
b100 R
1)
#1760000
0)
#1765000
b101 R
1)
#1770000
0)
#1775000
b110 R
1)
#1780000
0)
#1785000
b111 R
1)
#1790000
0)
#1795000
b0 R
0;
1)
#1800000
0)
#1805000
0F
1)
#1810000
0)
#1815000
1S
1+
1)
#1820000
0)
#1825000
1T
1)
#1830000
0)
#1835000
b1 R
1)
#1840000
0)
#1845000
b10 R
1)
#1850000
0)
#1855000
b11 R
1)
#1860000
0)
#1865000
b100 R
1)
#1870000
0)
#1875000
b101 R
1)
#1880000
0)
#1885000
b110 R
1)
#1890000
0)
#1895000
b111 R
1)
#1900000
0)
#1905000
b0 R
1;
1)
#1910000
0)
#1915000
b100 P
0S
1F
0+
1)
#1920000
0)
#1925000
b100 "
b100 O
0T
1)
#1930000
0)
#1935000
b1 R
1)
#1940000
0)
#1945000
b10 R
1)
#1950000
0)
#1955000
b11 R
1)
#1960000
0)
#1965000
b100 R
1)
#1970000
0)
#1975000
b101 R
1)
#1980000
0)
#1985000
b110 R
1)
#1990000
0)
#1995000
b111 R
1)
#2000000
0)
#2005000
b0 R
0;
1)
#2010000
0)
#2015000
0F
1)
#2020000
0)
#2025000
1S
1+
1)
#2030000
0)
#2035000
1T
1)
#2040000
0)
#2045000
b1 R
1)
#2050000
0)
#2055000
b10 R
1)
#2060000
0)
#2065000
b11 R
1)
#2070000
0)
#2075000
b100 R
1)
#2080000
0)
#2085000
b101 R
1)
#2090000
0)
#2095000
b110 R
1)
#2100000
0)
#2105000
b111 R
1)
#2110000
0)
#2115000
b0 R
1;
1)
#2120000
0)
#2125000
b100 P
1F
0S
0+
1)
#2130000
0)
#2135000
0T
b101 "
b101 O
1)
#2140000
0)
#2145000
b1 R
1)
#2150000
0)
#2155000
b10 R
1)
#2160000
0)
#2165000
b11 R
1)
#2170000
0)
#2175000
b100 R
1)
#2180000
0)
#2185000
b101 R
1)
#2190000
0)
#2195000
b110 R
1)
#2200000
0)
#2205000
b111 R
1)
#2210000
0)
#2215000
b0 R
0;
1)
#2220000
0)
#2225000
0F
1)
#2230000
0)
#2235000
1)
#2240000
0)
#2245000
1S
1+
1)
#2250000
0)
#2255000
1T
1)
#2260000
0)
#2265000
b1 R
1)
#2270000
0)
#2275000
b10 R
1)
#2280000
0)
#2285000
b11 R
1)
#2290000
0)
#2295000
b100 R
1)
#2300000
0)
#2305000
b101 R
1)
#2310000
0)
#2315000
b110 R
1)
#2320000
0)
#2325000
b111 R
1)
#2330000
0)
#2335000
b0 R
1;
1)
#2340000
0)
#2345000
b100 P
1F
0S
0+
1)
#2350000
0)
#2355000
0T
b110 "
b110 O
1)
#2360000
0)
#2365000
b1 R
1)
#2370000
0)
#2375000
b10 R
1)
#2380000
0)
#2385000
b11 R
1)
#2390000
0)
#2395000
b100 R
1)
#2400000
0)
#2405000
b101 R
1)
#2410000
0)
#2415000
b110 R
1)
#2420000
0)
#2425000
b111 R
1)
#2430000
0)
#2435000
b0 R
0;
1)
#2440000
0)
#2445000
0F
1)
#2450000
0)
#2455000
1S
1+
1)
#2460000
0)
