Verilog/ddsmini.v
//================================================================
//  SMART IRRIGATION SYSTEM
//  Modelled across all abstraction levels: Behavioral, Dataflow, and Structural
//================================================================

module smart_irrigation #(
    parameter NUM_USERS = 4,
    parameter WIDTH = 6, // 6-bit (0-63)
    parameter DEBOUNCE_WIDTH = 20
)(
    // ------------------- System Inputs -------------------
    input  wire clk,                // Main fast clock
    input  wire rst_n,              // Active low reset
    input  wire clk_1hz,            // 1-second clock for 24-hour timer

    // ------------------- Sensor Inputs -------------------
    input  wire flow_pulse_raw,     // Flow sensor pulse
    input  wire moisture_dry,       // 1 = dry
    input  wire rain,               // 1 = raining

    // ------------------- Control Inputs -------------------
    input  wire auto_cycle_start,           // Start automatic sequence
    input  wire [1:0] user_select_manual,   // Manual zone select
    input  wire reset_user,                 // Reset usage for CURRENT user
    input  wire quota_wr,                   // Write quota for CURRENT user
    input  wire [WIDTH-1:0] quota_set,      // Quota value to write
    input  wire manual_override,            // Force valve on (except rain/exhausted)

    // ------------------- System Outputs -------------------
    output reg  valve_on,
    output reg  [NUM_USERS-1:0] quota_exceeded,
    output reg  [WIDTH-1:0]     usage_out,
    output reg  [WIDTH-1:0]     quota_out,
    output wire flow_boost_on,
    output wire sequencer_active,
    output wire [1:0] current_zone
);

    //================================================================
    // LEVEL 1: STRUCTURAL MODEL
    //================================================================
    // Defines interconnection of modules, memories, and signals.

    reg [WIDTH-1:0] quota [0:NUM_USERS-1];  // Register array for water quota
    reg [WIDTH-1:0] usage [0:NUM_USERS-1];  // Register array for used water amount
    integer i;

    //================================================================
    // LEVEL 2: DATAFLOW MODEL — Sun Time Calculation
    //================================================================
    // Computes how data moves through signals using continuous assignments.

    reg [4:0] hour_cnt;        // 0–23 fits in 5 bits
    wire peak_time;            // Logical flag for peak sunlight hours (10AM–4PM)

    always @(posedge clk_1hz or negedge rst_n) begin
        if (!rst_n)
            hour_cnt <= 0;
        else if (hour_cnt == 23)
            hour_cnt <= 0;
        else
            hour_cnt <= hour_cnt + 1;
    end

    assign peak_time = (hour_cnt >= 5'd10) && (hour_cnt <= 5'd16);

    //================================================================
    // LEVEL 3: BEHAVIORAL MODEL — Zone Sequencer FSM
    //================================================================
    // Describes *what the system does* using algorithmic state transitions.

    localparam [2:0]
        S_IDLE   = 3'b000,
        S_ZONE_2 = 3'b001, // Priority 1
        S_ZONE_0 = 3'b010, // Priority 2
        S_ZONE_3 = 3'b011, // Priority 3
        S_ZONE_1 = 3'b100; // Priority 4

    reg [2:0] current_state;
    reg [1:0] internal_user_select_fsm;
    reg       internal_start_pulse;
    reg       internal_sequencer_active;

    reg irrigating_last;
    wire zone_finished_pulse = irrigating_last && !irrigating;

    // FSM Controls the automatic switching between zones
    always @(posedge clk or negedge rst_n) begin
        if (!rst_n) begin
            current_state <= S_IDLE;
            internal_start_pulse <= 1'b0;
        end else begin
            internal_start_pulse <= 1'b0;
            case (current_state)
                S_IDLE:
                    if (auto_cycle_start) begin
                        current_state <= S_ZONE_2;
                        internal_start_pulse <= 1'b1;
                    end
                S_ZONE_2:
                    if (zone_finished_pulse) begin
                        current_state <= S_ZONE_0;
                        internal_start_pulse <= 1'b1;
                    end
                S_ZONE_0:
                    if (zone_finished_pulse) begin
                        current_state <= S_ZONE_3;
                        internal_start_pulse <= 1'b1;
                    end
                S_ZONE_3:
                    if (zone_finished_pulse) begin
                        current_state <= S_ZONE_1;
                        internal_start_pulse <= 1'b1;
                    end
                S_ZONE_1:
                    if (zone_finished_pulse)
                        current_state <= S_IDLE;
                default:
                    current_state <= S_IDLE;
            endcase
        end
    end

    // FSM Output Mapping
    always @(*) begin
        case (current_state)
            S_IDLE:   begin internal_user_select_fsm = 2'b00; internal_sequencer_active = 1'b0; end
            S_ZONE_2: begin internal_user_select_fsm = 2'b10; internal_sequencer_active = 1'b1; end
            S_ZONE_0: begin internal_user_select_fsm = 2'b00; internal_sequencer_active = 1'b1; end
            S_ZONE_3: begin internal_user_select_fsm = 2'b11; internal_sequencer_active = 1'b1; end
            S_ZONE_1: begin internal_user_select_fsm = 2'b01; internal_sequencer_active = 1'b1; end
            default:  begin internal_user_select_fsm = 2'b00; internal_sequencer_active = 1'b0; end
        endcase
    end

    // Choose zone: automatic or manual
    wire [1:0] final_user_select = internal_sequencer_active ? internal_user_select_fsm : user_select_manual;

    assign sequencer_active = internal_sequencer_active;
    assign current_zone = final_user_select;

    //================================================================
    // LEVEL 4: STRUCTURAL MODEL — Module Instantiation
    //================================================================
    // The debounce module removes input noise using synchronizers and counters.

    wire flow_pulse_debounced;
    debounce_pulse #(.WIDTH(DEBOUNCE_WIDTH)) u_debounce (
        .clk(clk),
        .rst_n(rst_n),
        .raw_in(flow_pulse_raw),
        .clean_out(flow_pulse_debounced)
    );

    //================================================================
    // LEVEL 5: BEHAVIORAL + DATAFLOW — Main Control Logic
    //================================================================
    // This section mixes behavioral sequencing with dataflow relationships.

    reg irrigating;
    reg flow_pulse_last;
    wire [1:0] increment_val = peak_time ? 2'b10 : 2'b01; // Sunlight effect
    wire [WIDTH-1:0] max_val = {WIDTH{1'b1}};

    always @(posedge clk or negedge rst_n) begin
        if (!rst_n) begin
            irrigating <= 1'b0;
            flow_pulse_last <= 1'b0;
            irrigating_last <= 1'b0;
            for (i = 0; i < NUM_USERS; i = i + 1) begin
                usage[i] <= {WIDTH{1'b0}};
                quota[i] <= {WIDTH{1'b0}};
            end
            usage_out <= {WIDTH{1'b0}};
            quota_out <= {WIDTH{1'b0}};
        end else begin
            flow_pulse_last <= flow_pulse_debounced;
            irrigating_last <= irrigating;

            if (reset_user)
                usage[final_user_select] <= {WIDTH{1'b0}};

            if (quota_wr)
                quota[final_user_select] <= quota_set;

            // Start and Stop Conditions (Behavioral)
            if (internal_start_pulse && !irrigating && moisture_dry && !rain && !quota_exceeded[final_user_select])
                irrigating <= 1'b1;
            else if (irrigating && (!moisture_dry || rain || quota_exceeded[final_user_select]))
                irrigating <= 1'b0;

            // Flow Pulse Counting (Dataflow)
            if (valve_on && flow_pulse_debounced && !flow_pulse_last) begin
                if (usage[final_user_select] <= max_val - {{(WIDTH-2){1'b0}}, increment_val})
                    usage[final_user_select] <= usage[final_user_select] + {{(WIDTH-2){1'b0}}, increment_val};
                else
                    usage[final_user_select] <= max_val;
            end

            usage_out <= usage[final_user_select];
            quota_out <= quota[final_user_select];
        end
    end

    // Quota Exceeded Logic (Dataflow)
    always @(*) begin
        for (i = 0; i < NUM_USERS; i = i + 1)
            quota_exceeded[i] = (usage[i] >= quota[i]);
    end

    // Valve Control (Dataflow + Behavioral conditions)
    always @(*) begin
        if (rain)
            valve_on = 1'b0;
        else if (manual_override && !quota_exceeded[final_user_select])
            valve_on = 1'b1;
        else if (irrigating && !quota_exceeded[final_user_select])
            valve_on = 1'b1;
        else
            valve_on = 1'b0;
    end

    assign flow_boost_on = valve_on && peak_time; // Dataflow output

endmodule


//================================================================
// SUBMODULE: Debounce Pulse (Gate-Level Model Example)
//================================================================
// This module demonstrates a lower-level, gate-equivalent design.
// It filters mechanical switch noise using flip-flops and counters.

module debounce_pulse #(
    parameter WIDTH = 20
)(
    input wire clk,
    input wire rst_n,
    input wire raw_in,
    output reg clean_out
);
    reg [WIDTH-1:0] counter;
    reg raw_sync_0;
    reg raw_sync_1;

    always @(posedge clk or negedge rst_n) begin
        if (!rst_n) begin
            raw_sync_0 <= 1'b0;
            raw_sync_1 <= 1'b0;
            counter    <= {WIDTH{1'b0}};
            clean_out  <= 1'b0;
        end else begin
            raw_sync_0 <= raw_in;
            raw_sync_1 <= raw_sync_0;

            if (raw_sync_1 == clean_out)
                counter <= {WIDTH{1'b0}};
            else if (counter != {WIDTH{1'b1}})
                counter <= counter + 1'b1;
            else begin
                clean_out <= raw_sync_1;
                counter <= {WIDTH{1'b0}};
            end
        end
    end
endmodule

Verilog/ddsmini_tb.v
`timescale 1ns / 1ps
//================================================================
// TESTBENCH: Smart Irrigation System
//================================================================
// Simulates behavior of all abstraction levels:
// - FSM sequencing
// - Quota logic
// - Rain/Moisture control
// - Peak sunlight rate increase
//================================================================

module tb_smart_irrigation;

    // ------------------- Parameters -------------------
    parameter NUM_USERS = 4;
    parameter WIDTH = 6;
    parameter DEBOUNCE_WIDTH = 8;  // smaller for faster sim

    // ------------------- Testbench Signals -------------------
    reg clk;
    reg clk_1hz;
    reg rst_n;

    // Sensor inputs
    reg flow_pulse_raw;
    reg moisture_dry;
    reg rain;

    // Control inputs
    reg auto_cycle_start;
    reg [1:0] user_select_manual;
    reg reset_user;
    reg quota_wr;
    reg [WIDTH-1:0] quota_set;
    reg manual_override;

    // Outputs
    wire valve_on;
    wire [NUM_USERS-1:0] quota_exceeded;
    wire [WIDTH-1:0] usage_out;
    wire [WIDTH-1:0] quota_out;
    wire flow_boost_on;
    wire sequencer_active;
    wire [1:0] current_zone;

    // loop variable for testbench (Verilog-2001 compatible)
    integer i;

    // ------------------- DUT Instantiation -------------------
    smart_irrigation #(
        .NUM_USERS(NUM_USERS),
        .WIDTH(WIDTH),
        .DEBOUNCE_WIDTH(DEBOUNCE_WIDTH)
    ) DUT (
        .clk(clk),
        .rst_n(rst_n),
        .clk_1hz(clk_1hz),
        .flow_pulse_raw(flow_pulse_raw),
        .moisture_dry(moisture_dry),
        .rain(rain),
        .auto_cycle_start(auto_cycle_start),
        .user_select_manual(user_select_manual),
        .reset_user(reset_user),
        .quota_wr(quota_wr),
        .quota_set(quota_set),
        .manual_override(manual_override),
        .valve_on(valve_on),
        .quota_exceeded(quota_exceeded),
        .usage_out(usage_out),
        .quota_out(quota_out),
        .flow_boost_on(flow_boost_on),
        .sequencer_active(sequencer_active),
        .current_zone(current_zone)
    );

    //================================================================
    // VCD / Waveform dump
    //================================================================
    initial begin
        $dumpfile("smart_irrigation_auto.vcd");
        $dumpvars(0, tb_smart_irrigation);
    end

    //================================================================
    // CLOCK GENERATION
    //================================================================
    initial begin
        clk = 0;
        forever #5 clk = ~clk;      // 100 MHz main clock (period 10ns)
    end

    initial begin
        clk_1hz = 0;
        forever #500 clk_1hz = ~clk_1hz; // Simulated 1Hz = 1000ns period
    end

    //================================================================
    // TEST SEQUENCE
    //================================================================
    initial begin
        // Initialize signals
        rst_n = 0;
        flow_pulse_raw = 0;
        moisture_dry = 0;
        rain = 0;
        auto_cycle_start = 0;
        user_select_manual = 0;
        reset_user = 0;
        quota_wr = 0;
        quota_set = {WIDTH{1'b0}};
        manual_override = 0;

        // Reset Phase
        $display("\n---- SYSTEM RESET ----");
        #50;
        rst_n = 1;
        #100;

        // Assign initial quotas
        $display("---- SETTING INITIAL QUOTAS ----");
        for (i = 0; i < NUM_USERS; i = i + 1) begin
            quota_set = 6'd20 + (i * 5); // Each zone different quota
            user_select_manual = i[1:0];
            quota_wr = 1;
            #20;
            quota_wr = 0;
            #20;
        end

        // Start automatic sequence
        $display("---- START AUTO CYCLE ----");
        auto_cycle_start = 1;
        #20 auto_cycle_start = 0;
        moisture_dry = 1;  // soil is dry

        // Simulate watering activity (some pulses)
        repeat (10) begin
            // Generate water flow pulses (debounced module uses counter so pulses must persist)
            flow_pulse_raw = 1;
            #10;
            flow_pulse_raw = 0;
            #40;
        end

        // Simulate rain event
        $display("---- RAIN DETECTED ----");
        rain = 1;
        #200;
        rain = 0;

        // Simulate manual override
        $display("---- MANUAL OVERRIDE ACTIVATED ----");
        manual_override = 1;
        moisture_dry = 1;
        #200;
        manual_override = 0;

        // Simulate next zone switch (give some pulses)
        $display("---- NEXT ZONE TRIGGER ----");
        flow_pulse_raw = 0;
        moisture_dry = 1;
        repeat (5) begin
            flow_pulse_raw = 1; #10;
            flow_pulse_raw = 0; #30;
        end

        // Reset one zone manually
        $display("---- RESET USER 1 ----");
        user_select_manual = 2'd1;
        reset_user = 1;
        #20 reset_user = 0;

        // Wait a bit to observe behaviour then finish
        $display("---- SIMULATION COMPLETE ----");
        #500;
        $finish;
    end

    //================================================================
    // MONITOR OUTPUTS
    //================================================================
    always @(posedge clk) begin
        $display("T=%0t | Zone=%0d | Valve=%b | Rain=%b | Dry=%b | QuotaUsed=%0d | QuotaLimit=%0d | QuotaExceeded=%b | FlowBoost=%b | SeqActive=%b",
            $time, current_zone, valve_on, rain, moisture_dry, usage_out, quota_out, quota_exceeded, flow_boost_on, sequencer_active);
    end

endmodule

Verilog/smart_irrigation_auto.vcd
$date
	Sun Nov 02 23:20:34 2025
$end
$version
	Icarus Verilog
$end
$timescale
	1ps
$end
$scope module tb_smart_irrigation $end
$var wire 1 ! valve_on $end
$var wire 6 " usage_out [5:0] $end
$var wire 1 # sequencer_active $end
$var wire 6 $ quota_out [5:0] $end
$var wire 4 % quota_exceeded [3:0] $end
$var wire 1 & flow_boost_on $end
$var wire 2 ' current_zone [1:0] $end
$var parameter 32 ( DEBOUNCE_WIDTH $end
$var parameter 32 ) NUM_USERS $end
$var parameter 32 * WIDTH $end
$var reg 1 + auto_cycle_start $end
$var reg 1 , clk $end
$var reg 1 - clk_1hz $end
$var reg 1 . flow_pulse_raw $end
$var reg 1 / manual_override $end
$var reg 1 0 moisture_dry $end
$var reg 6 1 quota_set [5:0] $end
$var reg 1 2 quota_wr $end
$var reg 1 3 rain $end
$var reg 1 4 reset_user $end
$var reg 1 5 rst_n $end
$var reg 2 6 user_select_manual [1:0] $end
$var integer 32 7 i [31:0] $end
$scope module DUT $end
$var wire 1 + auto_cycle_start $end
$var wire 1 , clk $end
$var wire 1 - clk_1hz $end
$var wire 2 8 current_zone [1:0] $end
$var wire 1 & flow_boost_on $end
$var wire 1 . flow_pulse_raw $end
$var wire 1 / manual_override $end
$var wire 6 9 max_val [5:0] $end
$var wire 1 0 moisture_dry $end
$var wire 1 : peak_time $end
$var wire 6 ; quota_set [5:0] $end
$var wire 1 2 quota_wr $end
$var wire 1 3 rain $end
$var wire 1 4 reset_user $end
$var wire 1 5 rst_n $end
$var wire 1 # sequencer_active $end
$var wire 2 < user_select_manual [1:0] $end
$var wire 1 = zone_finished_pulse $end
$var wire 2 > increment_val [1:0] $end
$var wire 1 ? flow_pulse_debounced $end
$var wire 2 @ final_user_select [1:0] $end
$var parameter 32 A DEBOUNCE_WIDTH $end
$var parameter 32 B NUM_USERS $end
$var parameter 3 C S_IDLE $end
$var parameter 3 D S_ZONE_0 $end
$var parameter 3 E S_ZONE_1 $end
$var parameter 3 F S_ZONE_2 $end
$var parameter 3 G S_ZONE_3 $end
$var parameter 32 H WIDTH $end
$var reg 3 I current_state [2:0] $end
$var reg 1 J flow_pulse_last $end
$var reg 5 K hour_cnt [4:0] $end
$var reg 1 L internal_sequencer_active $end
$var reg 1 M internal_start_pulse $end
$var reg 2 N internal_user_select_fsm [1:0] $end
$var reg 1 O irrigating $end
$var reg 1 P irrigating_last $end
$var reg 4 Q quota_exceeded [3:0] $end
$var reg 6 R quota_out [5:0] $end
$var reg 6 S usage_out [5:0] $end
$var reg 1 ! valve_on $end
$var integer 32 T i [31:0] $end
$scope module u_debounce $end
$var wire 1 , clk $end
$var wire 1 . raw_in $end
$var wire 1 5 rst_n $end
$var parameter 32 U WIDTH $end
$var reg 1 ? clean_out $end
$var reg 8 V counter [7:0] $end
$var reg 1 W raw_sync_0 $end
$var reg 1 X raw_sync_1 $end
$upscope $end
$upscope $end
$upscope $end
$enddefinitions $end
$comment Show the parameter values. $end
$dumpall
b1000 U
b110 H
b11 G
b1 F
b100 E
b10 D
b0 C
b100 B
b1000 A
b110 *
b100 )
b1000 (
$end
#0
$dumpvars
0X
0W
b0 V
b100 T
b0 S
b0 R
b1111 Q
0P
0O
b0 N
0M
0L
b0 K
0J
b0 I
b0 @
0?
b1 >
0=
b0 <
b0 ;
0:
b111111 9
b0 8
bx 7
b0 6
05
04
03
02
b0 1
00
0/
0.
0-
0,
0+
b0 '
0&
b1111 %
b0 $
0#
b0 "
0!
$end
#5000
b100 T
1,
#10000
0,
#15000
b100 T
1,
#20000
0,
#25000
b100 T
1,
#30000
0,
#35000
b100 T
1,
#40000
0,
#45000
b100 T
1,
#50000
0,
15
#55000
1,
#60000
0,
#65000
1,
#70000
0,
#75000
1,
#80000
0,
#85000
1,
#90000
0,
#95000
1,
#100000
0,
#105000
1,
#110000
0,
#115000
1,
#120000
0,
#125000
1,
#130000
0,
#135000
1,
#140000
0,
#145000
1,
#150000
0,
12
b10100 1
b10100 ;
b0 7
#155000
b1110 %
b1110 Q
b100 T
1,
#160000
0,
#165000
b10100 $
b10100 R
1,
#170000
0,
02
#175000
1,
#180000
0,
#185000
1,
#190000
b1 '
b1 8
b1 @
0,
12
b1 6
b1 <
b11001 1
b11001 ;
b1 7
#195000
b1100 %
b1100 Q
b100 T
b0 $
b0 R
1,
#200000
0,
#205000
b11001 $
b11001 R
1,
#210000
0,
02
#215000
1,
#220000
0,
#225000
1,
#230000
b10 '
b10 8
b10 @
0,
12
b10 6
b10 <
b11110 1
b11110 ;
b10 7
#235000
b1000 %
b1000 Q
b100 T
b0 $
b0 R
1,
#240000
0,
#245000
b11110 $
b11110 R
1,
#250000
0,
02
#255000
1,
#260000
0,
#265000
1,
#270000
b11 '
b11 8
b11 @
0,
12
b11 6
b11 <
b100011 1
b100011 ;
b11 7
#275000
b0 %
b0 Q
b100 T
b0 $
b0 R
1,
#280000
0,
#285000
b100011 $
b100011 R
1,
#290000
0,
02
#295000
1,
#300000
0,
#305000
1,
#310000
0,
1+
b100 7
#315000
b10 '
b10 8
b10 @
1#
1L
b10 N
1M
b1 I
1,
#320000
0,
#325000
b11110 $
b11110 R
0M
1,
#330000
0,
1.
10
0+
#335000
1W
1,
#340000
0,
0.
#345000
1X
0W
1,
#350000
0,
#355000
b1 V
0X
1,
#360000
0,
#365000
b0 V
1,
#370000
0,
#375000
1,
#380000
0,
1.
#385000
1W
1,
#390000
0,
0.
#395000
1X
0W
1,
#400000
0,
#405000
b1 V
0X
1,
#410000
0,
#415000
b0 V
1,
#420000
0,
#425000
1,
#430000
0,
1.
#435000
1W
1,
#440000
0,
0.
#445000
1X
0W
1,
#450000
0,
#455000
b1 V
0X
1,
#460000
0,
#465000
b0 V
1,
#470000
0,
#475000
1,
#480000
0,
1.
#485000
1W
1,
#490000
0,
0.
#495000
1X
0W
1,
#500000
b1 K
0,
1-
#505000
b1 V
0X
1,
#510000
0,
#515000
b0 V
1,
#520000
0,
#525000
1,
#530000
0,
1.
#535000
1W
1,
#540000
0,
0.
#545000
1X
0W
1,
#550000
0,
#555000
b1 V
0X
1,
#560000
0,
#565000
b0 V
1,
#570000
0,
#575000
1,
#580000
0,
1.
#585000
1W
1,
#590000
0,
0.
#595000
1X
0W
1,
#600000
0,
#605000
b1 V
0X
1,
#610000
0,
#615000
b0 V
1,
#620000
0,
#625000
1,
#630000
0,
1.
#635000
1W
1,
#640000
0,
0.
#645000
1X
0W
1,
#650000
0,
#655000
b1 V
0X
1,
#660000
0,
#665000
b0 V
1,
#670000
0,
#675000
1,
#680000
0,
1.
#685000
1W
1,
#690000
0,
0.
#695000
1X
0W
1,
#700000
0,
#705000
b1 V
0X
1,
#710000
0,
#715000
b0 V
1,
#720000
0,
#725000
1,
#730000
0,
1.
#735000
1W
1,
#740000
0,
0.
#745000
1X
0W
1,
#750000
0,
#755000
b1 V
0X
1,
#760000
0,
#765000
b0 V
1,
#770000
0,
#775000
1,
#780000
0,
1.
#785000
1W
1,
#790000
0,
0.
#795000
1X
0W
1,
#800000
0,
#805000
b1 V
0X
1,
#810000
0,
#815000
b0 V
1,
#820000
0,
#825000
1,
#830000
0,
13
#835000
1,
#840000
0,
#845000
1,
#850000
0,
#855000
1,
#860000
0,
#865000
1,
#870000
0,
#875000
1,
#880000
0,
#885000
1,
#890000
0,
#895000
1,
#900000
0,
#905000
1,
#910000
0,
#915000
1,
#920000
0,
#925000
1,
#930000
0,
#935000
1,
#940000
0,
#945000
1,
#950000
0,
#955000
1,
#960000
0,
#965000
1,
#970000
0,
#975000
1,
#980000
0,
#985000
1,
#990000
0,
#995000
1,
#1000000
0,
0-
#1005000
1,
#1010000
0,
#1015000
1,
#1020000
0,
#1025000
1,
#1030000
1!
0,
1/
03
#1035000
1,
#1040000
0,
#1045000
1,
#1050000
0,
#1055000
1,
#1060000
0,
#1065000
1,
#1070000
0,
#1075000
1,
#1080000
0,
#1085000
1,
#1090000
0,
#1095000
1,
#1100000
0,
#1105000
1,
#1110000
0,
#1115000
1,
#1120000
0,
#1125000
1,
#1130000
0,
#1135000
1,
#1140000
0,
#1145000
1,
#1150000
0,
#1155000
1,
#1160000
0,
#1165000
1,
#1170000
0,
#1175000
1,
#1180000
0,
#1185000
1,
#1190000
0,
#1195000
1,
#1200000
0,
#1205000
1,
#1210000
0,
#1215000
1,
#1220000
0,
#1225000
1,
#1230000
0!
0,
1.
0/
#1235000
1W
1,
#1240000
0,
0.
#1245000
1X
0W
1,
#1250000
0,
#1255000
b1 V
0X
1,
#1260000
0,
#1265000
b0 V
1,
#1270000
0,
1.
#1275000
1W
1,
#1280000
0,
0.
#1285000
1X
0W
1,
#1290000
0,
#1295000
b1 V
0X
1,
#1300000
0,
#1305000
b0 V
1,
#1310000
0,
1.
#1315000
1W
1,
#1320000
0,
0.
#1325000
1X
0W
1,
#1330000
0,
#1335000
b1 V
0X
1,
#1340000
0,
#1345000
b0 V
1,
#1350000
0,
1.
#1355000
1W
1,
#1360000
0,
0.
#1365000
1X
0W
1,
#1370000
0,
#1375000
b1 V
0X
1,
#1380000
0,
#1385000
b0 V
1,
#1390000
0,
1.
#1395000
1W
1,
#1400000
0,
0.
#1405000
1X
0W
1,
#1410000
0,
#1415000
b1 V
0X
1,
#1420000
0,
#1425000
b0 V
1,
#1430000
0,
14
b1 6
b1 <
#1435000
1,
#1440000
0,
#1445000
1,
#1450000
0,
04
#1455000
1,
#1460000
0,
#1465000
1,
#1470000
0,
#1475000
1,
#1480000
0,
#1485000
1,
#1490000
0,
#1495000
1,
#1500000
b10 K
0,
1-
